bot_battle_game_client/__init__.py
bot_battle_game_client/bot_battle_game_client.py
bot_battle_game_client/env.py
bot_battle_game_client/py.typed
bot_battle_game_client-0.1.0.dist-info/METADATA
bot_battle_game_client-0.1.0.dist-info/WHEEL
bot_battle_game_client-0.1.0.dist-info/RECORD
