Metadata-Version: 2.4
Name: bot-battle-game-client
Version: 0.1.0
Summary: Add your description here
Author-email: Henry Jones <henryivesjones@gmail.com>
Requires-Python: >=3.9
Requires-Dist: httpx>=0.28.1
Requires-Dist: pydantic-settings>=2.9.1
Requires-Dist: pydantic>=2.11.4
